<odoo>
  <data>
    <!-- explicit list view definition -->
<!--
    <record model="ir.ui.view" id="natacion.list">
      <field name="name">natacion list</field>
      <field name="model">natacion.natacion</field>
      <field name="arch" type="xml">
        <list>
          <field name="name"/>
          <field name="value"/>
          <field name="value2"/>
        </list>
      </field>
    </record>
-->

    <!-- actions opening views on models -->

    <!-- Top menu item -->

    <menuitem name="natacion" id="natacion.menu_root_natacion"/>

    <!-- menu categories -->

    <menuitem name="Management" id="natacion.menu_management" parent="natacion.menu_root_natacion"/>
   
    <!-- actions -->

  </data>
</odoo>
